makerrepo-0.1.7.dist-info/licenses/LICENSE
mr/__init__.py
mr/constants.py
mr/artifacts/__init__.py
mr/artifacts/capture_image.py
mr/artifacts/data_types.py
mr/artifacts/decorator.py
mr/artifacts/registry.py
mr/artifacts/utils.py
mr/cmds/__init__.py
mr/cmds/aliase.py
mr/cmds/cli.py
mr/cmds/environment.py
mr/cmds/main.py
mr/cmds/artifacts/__init__.py
mr/cmds/artifacts/cli.py
mr/cmds/artifacts/main.py
mr/cmds/artifacts/ocp_data_types.py
mr/cmds/artifacts/utils.py
mr/data/cad_viewer.html
mr/data/three-cad-viewer-3.6.3.css
mr/data/three-cad-viewer-3.6.3.js
mr/data/utils.js
makerrepo-0.1.7.dist-info/METADATA
makerrepo-0.1.7.dist-info/WHEEL
makerrepo-0.1.7.dist-info/entry_points.txt
makerrepo-0.1.7.dist-info/top_level.txt
makerrepo-0.1.7.dist-info/RECORD
