Metadata-Version: 2.4
Name: makerrepo
Version: 0.1.7
Summary: Open source library that brings Manufacturing As Code concept into build123d ecosystem
Author-email: Fang-Pen Lin <fangpen@launchplatform.com>
License-Expression: MIT
Requires-Python: >=3.11
License-File: LICENSE
Requires-Dist: build123d>=0.10.0
Requires-Dist: click>=8.3.1
Requires-Dist: greenlet>=3.3.0
Requires-Dist: httpx>=0.25.0
Requires-Dist: ocp-vscode>=3.0.1
Requires-Dist: pip>=25.3
Requires-Dist: playwright>=1.40.0
Requires-Dist: pydantic>=2.12.5
Requires-Dist: rich>=13.7.1
Requires-Dist: venusian>=3.1.1
Dynamic: license-file
